{
	"poor": {
		"names": [
			"Juanete", "Joserico", "Maritornes", "Ananohache", "Luisenterio",
			"Carlisto", "Mañuel", "Antoñio", "Franco el bueno", "Perequitez",
			"Rosilda Marinta", "Juanancio Josuita", "Mariana Jorgina", "Josantonio", "Jutonio",
			"Liángel", "Anastamaria", "Luis Miguel", "María Isabel", "María Carmen",
			"Javier", "Francisca", "Jesús", "Eduardo", "Rosa",
			"Cristina", "Laura", "Andrea", "Sandra", "Patricia",
			"Rocío", "Sara", "Isabel", "Fernando", "Roberto",
			"Jorge", "Pablo", "Rafael", "Diego", "Raúl",
			"Antonia", "Lucía", "Pilar", "Verónica", "Teresa",
			"Rosa María", "Dolores", "Carmen", "Josefa", "Ángeles",
			"Juanamigo", "Joselindo", "Maritornes", "Anacleto", "Luisillo", 
			"Carlomagno", "Manolín", "Antoñeta", "Francisquete", "Pedrín", 
			"Rosarillo", "Juancho",  "Marianito", "Josefinita", "Justino", 
			"Leocadio", "Anarosa", "Ricardete", "Fernandito", "Pepelucho", 
			"Laurita", "Nicolasa","Elenita","Felipón", "Gregoriete", "Hugoncito", "Isabelica",
			"Ana Belén", "María Dolores", "Juan Manuel", "José Luis", "María Teresa",
			"Ana María", "Francisco Javier", "María Jesús", "Antonia María", "María Pilar",
			"Manuel Jesús", "Carmen María", "José Manuel", "Juan José", "María José",
			"José Antonio", "Ana María", "Francisco José", "José María", "Juan Antonio",
			"María Carmen", "José Luis", "María Isabel", "José Carlos", "Antonio José",
			"José Manuel", "María Rosa", "María Ángeles", "Manuel José", "Antonio Jesús",
			"José Miguel", "Ana Isabel", "Juan Carlos", "Ana María", "Miguel Ángel",
			"Francisco Manuel", "Ana Rosa", "José Ramón", "Francisco Javier", "Ana Teresa",
			"Mohammed", "Olga", "Chen", "Aisha", "Chinwe",
			"Jorge", "Maria", "Wei", "Fatima", "Emeka",
			"Sergio", "Natasha", "Wang", "Yasmin", "Kwame",
			"Ahmed", "Elena", "Li", "Hassan", "Ngozi",
			"Muhammad", "Svetlana", "Zhang", "Leila", "Olu",
			"Ali", "Larisa", "Sun", "Amira", "Obi",
			"Youssef", "Tatiana", "Kim", "Huda", "Chukwu",
			"Abdullah", "Alina","Jamilah", "Olatunji",
			"Omar", "Anastasia", "Choi", "Safia", "Chinedu",
			"Abdul", "Irina", "Raj", "Zara", "Uchenna",
			"Amin", "Natalia", "Subramanian", "Rania", "Nnamdi",
			"Jibril", "Yelena", "Rao", "Jamila", "Chidi",
			"Nabil", "Eva", "Khan", "Laila", "Ayo",
			"Osama", "Yulia", "Singh", "Nadia", "Obinna",
			"Hussein", "Anna", "Kumar", "Amani", "Chukwudi",
			"Abdel", "Yelizaveta", "Lee", "Samira", "Chukwuma",
			"Khaled", "Elena", "Fang", "Amina", "Chigozie",
			"Ahmad", "Alena", "Wu", "Hala", "Chinonye",
			"Bilal", "Lena", "Patel", "Lina", "Eze",
			"Rubém", "Tio Stan"
		],
	"surnames": [
			"Diazfano", "Garcíez", "Fernánez", "Gonzálvarez", "Rodrítez", "Lomartín",
			"Sanchimenez", "Perezalez", "Martirízto", "Gomernández", "Ruizález",
			"Diazánchez", "Álvarezto", "Morenández", "Muñómenez", "Alonsíaz",
			"Gutiérrezález", "Romérez", "Navárez", "Torrezález", "Domínguiz",
			"Ramírezález", "Serránz", "Blanquéz", "Sanrro", "Castérez",
			"Suárezález", "Ortéz", "Rubíaz", "Molíno", "Delgádez",
			"Ramórez", "Moráles", "Ortíz", "Marínz", "Iglesíez",
			"Medína", "Nuñéz", "Garrído", "Castíllo", "Cortéz",
			"Lozánno", "Guerréro", "Santós", "Canó", "Prietó",
			"Cruzéz", "Méndez", "Calvó", "Vidál", "Gallegó",
			"Herréra", "Cabrérz", "Florés", "Peñá", "Leónz",
			"Márquez", "Campós", "Vegá", "Fuentés", "Carrascó",
			"Diéz", "Reyés", "Caballéro", "Nietó", "Pascuál",
			"Aguilár", "Santánna", "Herréro", "Ferrér", "Lorenzó",
			"Giménz", "Hidágo", "Monteró", "Ibáñez", "Santiáguez"
		]
	},
	"rich": {
		"names": [
			"Santiagini", "Isabelina", "Javiescu", "Carmentratra", "Carlinios", 
			"María", "Juan", "Sofía", "Diego", "Elena", 
			"Fernando", "Ana", "Álvaro", "Beatriz", "Ignacio", 
			"Marta", "Pedro", "Victoria", "Alejandro", "Eva", 
			"Pablo", "Adriana", "Luis", "Silvia", "José",  "Park", 
			"Lorena", "Jorge", "Paula", "Rafael", "Lucía", 
			"Francisco", "Mónica", "Gonzalo", "Raquel", "Miguel", 
			"Nuria", "Joaquín", "Lourdes", "Ricardo", "Marina", 
			"Daniel", "Verónica", "Guillermo", "Patricia", "Manuel", 
			"Isabel", "Ángel", "Cristina", "David", "Raquel",
			"Alexander", "Charlotte", "William", "Elizabeth", "James", 
			"Victoria", "Henry", "Olivia", "Charles", "Beatrice", 
			"Edward", "Alexandra", "George", "Margaret", "Christopher", 
			"Catherine", "Nicholas", "Caroline", "Sebastian", "Eleanor", 
			"Andrew", "Isabella", "Jonathan", "Sophia", "David", 
			"Grace", "Richard", "Amelia", "Jonathan", "Arabella", 
			"Phillip", "Penelope", "Benjamin", "Camilla", "Frederick", 
			"Juliet", "Michael", "Louisa", "Thomas", "Madeleine", 
			"Robert", "Cecilia", "Daniel", "Annabelle", "Christopher", 
			"Rosalind", "Patrick", "Aurelia", "Timothy", "Charlotte",
			"Cayetano", "Cayetanito", "Cayetana", "Amancio"
		],
	"surnames": [
			"Azmondeo", "Moráles", "Ortíz", "Marínz", "Iglesíez", "Medína",
			"Nuñéz", "Garrído", "Castíllo", "Cortéz", "Lozánno",
			"Guerréro", "Santós", "Canó", "Prietó", "Cruzéz",
			"Méndez", "Calvó", "Vidál", "Gallegó", "Herréra",
			"Cabrérz", "Florés", "Peñá", "Leónz", "Márquez",
			"Campós", "Vegá", "Fuentés", "Carrascó", "Diéz",
			"Reyés", "Caballéro", "Nietó", "Pascuál", "Aguilár",
			"Santánna", "Herréro", "Ferrér", "Lorenzó", "Giménz",
			"Hidágo", "Monteró", "Ibáñez", "Santiáguez", "Ramírezález",
			"Serránz", "Blanquéz", "Sanrro", "Castérez", "Suárezález",
			"Bezos", "Arnault", "Gates", "Buffett", "Zuckerberg",
			"Walton", "Ambani", "Slim", "Koch", "Bloomberg",
			"Ortega", "Ellison", "Mars", "Al Saud", "Kwok",
			"Johnson", "Lauder", "Pritzker", "Rothschild", "Bettencourt",
			"Page", "Brin", "Walton", "Ma", "Albrecht",
			"Hoffmann", "Musk", "Slim", "Albrecht", "Koch",
			"Mars", "Walton", "Koch", "Cargill", "Mars",
			"Al Saud", "Cargill", "Kwok", "Hoffmann", "Mars"
		]
	}
}
